<annotation>
	<folder>resized_image</folder>
	<filename>457615224.jpg</filename>
	<path>/Users/nguyenminh/Downloads/Projects/ML/tswift-detection/resized_image/457615224.jpg</path>
	<source>
		<database>Unknown</database>
	</source>
	<size>
		<width>420</width>
		<height>600</height>
		<depth>3</depth>
	</size>
	<segmented>0</segmented>
	<object>
		<name>tswift</name>
		<pose>Unspecified</pose>
		<truncated>0</truncated>
		<difficult>0</difficult>
		<bndbox>
			<xmin>44</xmin>
			<ymin>33</ymin>
			<xmax>381</xmax>
			<ymax>416</ymax>
		</bndbox>
	</object>
</annotation>
