<annotation>
	<folder>resized_image</folder>
	<filename>taylor_swift_30a65df5_ae82_46b5_9ab9_e5bea4e1e28a.jpg</filename>
	<path>/Users/nguyenminh/Downloads/Projects/ML/tswift-detection/resized_image/taylor_swift_30a65df5_ae82_46b5_9ab9_e5bea4e1e28a.jpg</path>
	<source>
		<database>Unknown</database>
	</source>
	<size>
		<width>598</width>
		<height>600</height>
		<depth>3</depth>
	</size>
	<segmented>0</segmented>
	<object>
		<name>tswift</name>
		<pose>Unspecified</pose>
		<truncated>0</truncated>
		<difficult>0</difficult>
		<bndbox>
			<xmin>225</xmin>
			<ymin>4</ymin>
			<xmax>386</xmax>
			<ymax>203</ymax>
		</bndbox>
	</object>
</annotation>
